{
    "id": 81,
    "name": "Analgesics — NSAIDs and Acetaminophen (Study 3 New-User Washout)",
    "description": "All systemic analgesic\/antipyretic agents for new-user washout. Both arms must have no prior NSAID or acetaminophen use in 365 days before index date.",
    "expression_json": {
        "items": []
    },
    "author_id": 117,
    "is_public": true,
    "tags": [
        "study-3",
        "analgesics",
        "washout",
        "NSAIDs",
        "acetaminophen"
    ],
    "created_at": null,
    "updated_at": null,
    "deleted_at": null,
    "items": [
        {
            "id": 365,
            "concept_set_id": 81,
            "concept_id": 1177480,
            "is_excluded": false,
            "include_descendants": true,
            "include_mapped": false,
            "created_at": "2026-03-19T23:51:25.000000Z",
            "updated_at": "2026-03-19T23:51:25.000000Z"
        },
        {
            "id": 366,
            "concept_set_id": 81,
            "concept_id": 1115008,
            "is_excluded": false,
            "include_descendants": true,
            "include_mapped": false,
            "created_at": "2026-03-19T23:51:25.000000Z",
            "updated_at": "2026-03-19T23:51:25.000000Z"
        },
        {
            "id": 367,
            "concept_set_id": 81,
            "concept_id": 1118084,
            "is_excluded": false,
            "include_descendants": true,
            "include_mapped": false,
            "created_at": "2026-03-19T23:51:25.000000Z",
            "updated_at": "2026-03-19T23:51:25.000000Z"
        },
        {
            "id": 368,
            "concept_set_id": 81,
            "concept_id": 1124300,
            "is_excluded": false,
            "include_descendants": true,
            "include_mapped": false,
            "created_at": "2026-03-19T23:51:25.000000Z",
            "updated_at": "2026-03-19T23:51:25.000000Z"
        },
        {
            "id": 369,
            "concept_set_id": 81,
            "concept_id": 1195492,
            "is_excluded": false,
            "include_descendants": true,
            "include_mapped": false,
            "created_at": "2026-03-19T23:51:25.000000Z",
            "updated_at": "2026-03-19T23:51:25.000000Z"
        },
        {
            "id": 370,
            "concept_set_id": 81,
            "concept_id": 1178663,
            "is_excluded": false,
            "include_descendants": true,
            "include_mapped": false,
            "created_at": "2026-03-19T23:51:25.000000Z",
            "updated_at": "2026-03-19T23:51:25.000000Z"
        },
        {
            "id": 371,
            "concept_set_id": 81,
            "concept_id": 1136980,
            "is_excluded": false,
            "include_descendants": true,
            "include_mapped": false,
            "created_at": "2026-03-19T23:51:25.000000Z",
            "updated_at": "2026-03-19T23:51:25.000000Z"
        },
        {
            "id": 372,
            "concept_set_id": 81,
            "concept_id": 1150345,
            "is_excluded": false,
            "include_descendants": true,
            "include_mapped": false,
            "created_at": "2026-03-19T23:51:25.000000Z",
            "updated_at": "2026-03-19T23:51:25.000000Z"
        },
        {
            "id": 373,
            "concept_set_id": 81,
            "concept_id": 1113648,
            "is_excluded": false,
            "include_descendants": true,
            "include_mapped": false,
            "created_at": "2026-03-19T23:51:25.000000Z",
            "updated_at": "2026-03-19T23:51:25.000000Z"
        },
        {
            "id": 374,
            "concept_set_id": 81,
            "concept_id": 1146810,
            "is_excluded": false,
            "include_descendants": true,
            "include_mapped": false,
            "created_at": "2026-03-19T23:51:25.000000Z",
            "updated_at": "2026-03-19T23:51:25.000000Z"
        },
        {
            "id": 375,
            "concept_set_id": 81,
            "concept_id": 1236607,
            "is_excluded": false,
            "include_descendants": true,
            "include_mapped": false,
            "created_at": "2026-03-19T23:51:25.000000Z",
            "updated_at": "2026-03-19T23:51:25.000000Z"
        },
        {
            "id": 376,
            "concept_set_id": 81,
            "concept_id": 1112807,
            "is_excluded": false,
            "include_descendants": true,
            "include_mapped": false,
            "created_at": "2026-03-19T23:51:25.000000Z",
            "updated_at": "2026-03-19T23:51:25.000000Z"
        },
        {
            "id": 377,
            "concept_set_id": 81,
            "concept_id": 1125315,
            "is_excluded": false,
            "include_descendants": true,
            "include_mapped": false,
            "created_at": "2026-03-19T23:51:25.000000Z",
            "updated_at": "2026-03-19T23:51:25.000000Z"
        }
    ]
}