{
    "id": 584,
    "name": "CD2_BENIGN_URINARY",
    "description": "Benign neoplasm of urinary organs — FinnGen Endpoint Library (DF14). Source: https:\/\/finngen.fi. Note: cohort generation against a CDM is not yet implemented for this shape; copy to a custom cohort first.",
    "expression_json": {
        "kind": "finngen_endpoint",
        "tags": [
            "#CD2"
        ],
        "level": "2",
        "parent": "D10-D36",
        "release": "df14",
        "coverage": {
            "pct": 1,
            "bucket": "FULLY_MAPPED",
            "n_tokens_total": 2,
            "n_tokens_resolved": 2
        },
        "conditions": null,
        "provenance": {
            "source_row": 337,
            "imported_at": "2026-04-17T19:56:38+00:00",
            "source_file": "FINNGEN_ENDPOINTS_DF14_Final_2026-02-13_public.xlsx",
            "importer_version": "1.0.0"
        },
        "hd_mainonly": false,
        "cod_mainonly": false,
        "source_codes": {
            "hd_icd_8": {
                "raw": null,
                "patterns": []
            },
            "hd_icd_9": {
                "raw": null,
                "patterns": []
            },
            "kela_atc": {
                "raw": null,
                "patterns": []
            },
            "oper_nom": {
                "raw": null,
                "patterns": []
            },
            "canc_topo": {
                "raw": null,
                "patterns": []
            },
            "cod_icd_8": {
                "raw": null,
                "patterns": []
            },
            "cod_icd_9": {
                "raw": null,
                "patterns": []
            },
            "hd_icd_10": {
                "raw": "D30",
                "patterns": [
                    "D30"
                ]
            },
            "canc_behav": {
                "raw": null,
                "patterns": []
            },
            "canc_morph": {
                "raw": null,
                "patterns": []
            },
            "cod_icd_10": {
                "raw": "D30",
                "patterns": [
                    "D30"
                ]
            },
            "kela_reimb": {
                "raw": null,
                "patterns": []
            },
            "outpat_icd": {
                "raw": null,
                "patterns": []
            },
            "hd_icd_8_excl": {
                "raw": null,
                "patterns": []
            },
            "hd_icd_9_excl": {
                "raw": null,
                "patterns": []
            },
            "hd_icd_10_excl": {
                "raw": null,
                "patterns": []
            },
            "kela_reimb_icd": {
                "raw": null,
                "patterns": []
            }
        },
        "spec_version": "1.0",
        "pre_conditions": null,
        "coverage_bucket": "FULLY_MAPPED",
        "sex_restriction": null,
        "coverage_profile": "partial",
        "include_endpoints": [
            "CD2_BENIGN_KIDNEY",
            "CD2_BENIGN_RENALPELVIS",
            "CD2_BENIGN_URETER",
            "CD2_BENIGN_BLADDER",
            "CD2_BENIGN_URETHRA",
            "CD2_BENIGN_URINARY_NOS"
        ],
        "resolved_concepts": {
            "truncated": false,
            "drugs_standard": [],
            "source_concept_ids": [
                1567791,
                1567792,
                1567793,
                1567794,
                35206594,
                35206595,
                35206597,
                45537904,
                45552342,
                45552343,
                45557070,
                45561908,
                45571608,
                45595745,
                45595746,
                45600588,
                45605350
            ],
            "conditions_standard": [
                78706,
                195498,
                200671,
                198103,
                201824,
                196377,
                37310596,
                37310611,
                36684823,
                37310612,
                36684822,
                37310609
            ]
        }
    },
    "author_id": 117,
    "is_public": true,
    "version": 1,
    "created_at": "2026-04-16T23:55:51.000000Z",
    "updated_at": "2026-04-17T19:56:38.000000Z",
    "deleted_at": null,
    "tags": [
        "finngen-endpoint",
        "finngen:df14",
        "#CD2"
    ],
    "share_token": null,
    "share_expires_at": null,
    "domain": "finngen-endpoint",
    "quality_tier": "draft",
    "deprecated_at": null,
    "superseded_by": null,
    "coverage_profile": "partial"
}