{
    "id": 2782,
    "name": "M13_DORSOPATHY",
    "description": "Dorsopathies — FinnGen Endpoint Library (DF14). Source: https:\/\/finngen.fi. Note: cohort generation against a CDM is not yet implemented for this shape; copy to a custom cohort first.",
    "expression_json": {
        "kind": "finngen_endpoint",
        "tags": [
            "#M13",
            "#GASTRO_CM"
        ],
        "level": "2",
        "parent": null,
        "release": "df14",
        "coverage": {
            "pct": 1,
            "bucket": "FULLY_MAPPED",
            "n_tokens_total": 14,
            "n_tokens_resolved": 14
        },
        "conditions": null,
        "provenance": {
            "source_row": 2535,
            "imported_at": "2026-04-17T00:17:38+00:00",
            "source_file": "FINNGEN_ENDPOINTS_DF14_Final_2026-02-13_public.xlsx",
            "importer_version": "1.0.0"
        },
        "hd_mainonly": false,
        "cod_mainonly": false,
        "source_codes": {
            "hd_icd_8": {
                "raw": null,
                "patterns": []
            },
            "hd_icd_9": {
                "raw": null,
                "patterns": []
            },
            "kela_atc": {
                "raw": null,
                "patterns": []
            },
            "oper_nom": {
                "raw": null,
                "patterns": []
            },
            "canc_topo": {
                "raw": null,
                "patterns": []
            },
            "cod_icd_8": {
                "raw": null,
                "patterns": []
            },
            "cod_icd_9": {
                "raw": null,
                "patterns": []
            },
            "hd_icd_10": {
                "raw": "M4|M5[0-5]",
                "patterns": [
                    "M4",
                    "M50",
                    "M51",
                    "M52",
                    "M53",
                    "M54",
                    "M55"
                ]
            },
            "canc_behav": {
                "raw": null,
                "patterns": []
            },
            "canc_morph": {
                "raw": null,
                "patterns": []
            },
            "cod_icd_10": {
                "raw": "M4|M5[0-5]",
                "patterns": [
                    "M4",
                    "M50",
                    "M51",
                    "M52",
                    "M53",
                    "M54",
                    "M55"
                ]
            },
            "kela_reimb": {
                "raw": null,
                "patterns": []
            },
            "outpat_icd": {
                "raw": null,
                "patterns": []
            },
            "hd_icd_8_excl": {
                "raw": null,
                "patterns": []
            },
            "hd_icd_9_excl": {
                "raw": null,
                "patterns": []
            },
            "hd_icd_10_excl": {
                "raw": null,
                "patterns": []
            },
            "kela_reimb_icd": {
                "raw": null,
                "patterns": []
            }
        },
        "spec_version": "1.0",
        "pre_conditions": null,
        "coverage_bucket": "FULLY_MAPPED",
        "sex_restriction": null,
        "include_endpoints": [
            "M13_DEFORMDORSO",
            "M13_SPONDYLOPATHY",
            "M13_CERVICDISC",
            "M13_INTERVERTEB",
            "M13_DORSOPATHYOTH",
            "M13_DORSALGIA",
            "M13_ENTESOPATHYLOW"
        ],
        "resolved_concepts": {
            "truncated": true,
            "drugs_standard": [],
            "source_concept_ids": [
                9815,
                9816,
                9817,
                9818,
                9819,
                9820,
                9821,
                9822,
                9823,
                9824,
                9825,
                9826,
                9827,
                9828,
                9829,
                9830,
                9831,
                9832,
                766401,
                766402,
                766403,
                766404,
                766405,
                766406,
                766407,
                766408,
                766409,
                766410,
                766411,
                766412,
                766413,
                766414,
                1102736,
                1102737,
                1102738,
                1102739,
                1102740,
                1102741,
                1102742,
                1102743,
                1326707,
                1326708,
                1570624,
                1570625,
                1570626,
                1570627,
                1570628,
                1570629,
                1570630,
                1570631,
                1570632,
                1570633,
                1570634,
                1570635,
                1570636,
                1570637,
                1570638,
                1570639,
                1570640,
                1570641,
                1570642,
                1570643,
                1570644,
                1570645,
                1570646,
                1570647,
                1570648,
                1570649,
                1570650,
                1570651,
                1570652,
                1570653,
                1570654,
                1570655,
                1570656,
                1570657,
                1570658,
                1570659,
                1570660,
                1570661,
                1570662,
                1570663,
                1570664,
                1570665,
                1570666,
                1570667,
                1570668,
                1570669,
                1570670,
                1570671,
                1570672,
                1570673,
                1570674,
                1570675,
                1570676,
                1570677,
                1570678,
                1570679,
                1570680,
                1570681,
                1570682,
                1570683,
                1570684,
                1570685,
                1570686,
                1570687,
                1570688,
                1570689,
                1570690,
                1570691,
                1570692,
                1570693,
                1570694,
                1570695,
                1570696,
                1570697,
                1570698,
                1570699,
                1570700,
                1570701,
                1570702,
                1570703,
                1570704,
                1570705,
                1570706,
                35208847,
                35208848,
                35208849,
                35208850,
                35208859,
                35208869,
                35208870,
                35208871,
                35208953,
                35208954,
                35208955,
                35208956,
                35208966,
                35208967,
                35208968,
                35208969,
                35208970,
                35208971,
                37200720,
                37200721,
                37200722,
                37200723,
                37200724,
                37200725,
                37200726,
                37200727,
                37200728,
                37200729,
                37200730,
                37200731,
                37200732,
                37200733,
                37200734,
                37200735,
                37200736,
                37200737,
                37200738,
                37200739,
                37200740,
                37200741,
                37200742,
                37200743,
                37402534,
                37402535,
                37402536,
                37402537,
                37402538,
                37402539,
                37402540,
                45533832,
                45533833,
                45533834,
                45533835,
                45533836,
                45533837,
                45533838,
                45533839,
                45533840,
                45533841,
                45533842,
                45533843,
                45533844,
                45533845,
                45533848,
                45533849,
                45533850,
                45533851,
                45533852,
                45533853,
                45533854,
                45533855,
                45533856,
                45533857,
                45533858,
                45533859,
                45533860,
                45533861,
                45533862,
                45533863,
                45533864,
                45533865,
                45533866,
                45533867,
                45533868,
                45538754,
                45538755,
                45538756,
                45538757,
                45538758,
                45538759,
                45538761,
                45538762,
                45538763,
                45538765,
                45538767,
                45538769,
                45538770,
                45538772,
                45538773,
                45538774,
                45538775,
                45538776,
                45538777,
                45538778,
                45538779,
                45538780,
                45538781,
                45538782,
                45538783,
                45538784,
                45538785,
                45538786,
                45538788,
                45538789,
                45543566,
                45543567,
                45543569,
                45543570,
                45543571,
                45543572,
                45543573,
                45543574,
                45543576,
                45543577,
                45543578,
                45543579,
                45543580,
                45543581,
                45543582,
                45543583,
                45543584,
                45543585,
                45543586,
                45543587,
                45543588,
                45543589,
                45543590,
                45543592,
                45543593,
                45543594,
                45543595,
                45543596,
                45543597,
                45543598,
                45543599,
                45543600,
                45543601,
                45543602,
                45543603,
                45543606,
                45543607,
                45543608,
                45543609,
                45543610,
                45543611,
                45543612,
                45543613,
                45548405,
                45548406,
                45548409,
                45548410,
                45548412,
                45548413,
                45548414,
                45548415,
                45548416,
                45548417,
                45548418,
                45548419,
                45548420,
                45548421,
                45548422,
                45548423,
                45548424,
                45548425,
                45548426,
                45548427,
                45548429,
                45548430,
                45548431,
                45548432,
                45548433,
                45548434,
                45548435,
                45548436,
                45548437,
                45548439,
                45548440,
                45548441,
                45548442,
                45548443,
                45548444,
                45553176,
                45553177,
                45553178,
                45553179,
                45553180,
                45553182,
                45553184,
                45553185,
                45553186,
                45553187,
                45553188,
                45553189,
                45553190,
                45553191,
                45553192,
                45553193,
                45553194,
                45553195,
                45553196,
                45553197,
                45553198,
                45553199,
                45553200,
                45553201,
                45553202,
                45553204,
                45553206,
                45557870,
                45557871,
                45557872,
                45557873,
                45557874,
                45557875,
                45557876,
                45557877,
                45557878,
                45557880,
                45557881,
                45557882,
                45557883,
                45557884,
                45557885,
                45557886,
                45557889,
                45557890,
                45557891,
                45557892,
                45557893,
                45557894,
                45557895,
                45557896,
                45557897,
                45557898,
                45557899,
                45557901,
                45557902,
                45557903,
                45562712,
                45562713,
                45562715,
                45562716,
                45562717,
                45562718,
                45562719,
                45562721,
                45562722,
                45562724,
                45562725,
                45562726,
                45562727,
                45562728,
                45562729,
                45562730,
                45562731,
                45562732,
                45562733,
                45562735,
                45562736,
                45562737,
                45562738,
                45562739,
                45562740,
                45562741,
                45562743,
                45562744,
                45562746,
                45562748,
                45562749,
                45567550,
                45567551,
                45567552,
                45567553,
                45567554,
                45567555,
                45567556,
                45567557,
                45567558,
                45567560,
                45567561,
                45567562,
                45567563,
                45567564,
                45567565,
                45567566,
                45567567,
                45567568,
                45567569,
                45567570,
                45567573,
                45567574,
                45567575,
                45567576,
                45567578,
                45567579,
                45567580,
                45572449,
                45572450,
                45572451,
                45572452,
                45572454,
                45572456,
                45572457,
                45572458,
                45572459,
                45572460,
                45572461,
                45572462,
                45572463,
                45572465,
                45572466,
                45572467,
                45572468,
                45572469,
                45572470,
                45572471,
                45577250,
                45577251,
                45577252,
                45577254,
                45577255,
                45577256,
                45577258,
                45577259,
                45577260,
                45577261,
                45577262,
                45577264,
                45577265,
                45577266,
                45577267,
                45577268,
                45577269,
                45577270,
                45577271,
                45577272,
                45577273,
                45577274,
                45577275,
                45577276,
                45577277,
                45577278,
                45577279,
                45577281,
                45577282,
                45577283,
                45577284,
                45577285,
                45577286,
                45582133,
                45582134,
                45582135,
                45582136,
                45582137,
                45582138,
                45582139,
                45582140,
                45582141,
                45582142,
                45582143,
                45582144,
                45582145,
                45582146,
                45582147
            ],
            "conditions_standard": [
                4001458,
                45772068,
                45770877,
                45757329,
                45757330,
                138841,
                4222001,
                4203556,
                4203555,
                4204781,
                37017494,
                1077466,
                1077506,
                194133,
                4160900,
                443769,
                43531133,
                74132,
                136788,
                4119307,
                73302,
                4147660,
                4214530,
                4069646,
                73012,
                72418,
                4069935,
                4067872,
                253009,
                4069943,
                44782549,
                433565,
                4001643,
                4344612,
                4167097,
                4187244,
                4138152,
                4346965,
                4134171,
                437082,
                4153359,
                75347,
                4001298,
                4067312,
                4046205,
                4262590,
                4227449,
                4032003,
                434656,
                4102334,
                4081173,
                138519,
                4157453,
                77079,
                77961,
                75908,
                81665,
                4141028,
                139906,
                4067313,
                40483292,
                314131,
                75344,
                78832,
                46287150,
                4251304,
                80816,
                80496,
                4260918,
                4345332,
                4169580,
                4216397,
                372409,
                4001450,
                134736,
                4000965,
                81939,
                4135077,
                440814,
                4182166,
                4208390,
                81660,
                77639,
                24134,
                312998,
                40482807,
                4344391,
                4179319,
                195906,
                4266078,
                74125,
                79119,
                608177,
                608180,
                4068616,
                37207747,
                40305987,
                443795,
                80497,
                436787,
                4247136,
                4134122,
                37171182,
                37171155,
                37207746,
                37018842,
                4184256,
                40481975,
                4183247,
                4068628,
                4040720,
                36715562,
                44783242,
                4346975,
                74130,
                80813,
                321661,
                37207749,
                4207936,
                442775,
                37171115,
                765582,
                45757669,
                601051,
                36713107,
                4001454,
                436785,
                37171158,
                37207744,
                37171157,
                4216083,
                37017436,
                37207796,
                4002139,
                198520,
                4110914,
                435041,
                46273238,
                46273239,
                37171147,
                4300489,
                4048684,
                141104,
                74635,
                37171113,
                4006163,
                37170862,
                4145719,
                37171152,
                4194739,
                139110,
                4185356,
                4067311,
                37207657,
                37310660,
                4068617,
                4308802,
                4152592,
                1076980,
                4184403,
                4184423,
                37171150,
                75897,
                141941,
                37171161,
                318522,
                4243940,
                37171058,
                4194890,
                37312612,
                4207935,
                434449,
                137548,
                4134121,
                37171060,
                37171156,
                4347307,
                4001456,
                37170863,
                4001455,
                4338669,
                4194891,
                4067539,
                37207745,
                37171057,
                37170858,
                4002140,
                4002143,
                4273693,
                137858,
                37171114,
                37171183,
                37167143,
                4000963,
                37171148,
                321389,
                4000964,
                37171059,
                4302686,
                37207748,
                4068482,
                4002142
            ]
        }
    },
    "author_id": 117,
    "is_public": true,
    "version": 1,
    "created_at": "2026-04-16T23:56:10.000000Z",
    "updated_at": "2026-04-17T00:17:38.000000Z",
    "deleted_at": null,
    "tags": [
        "finngen-endpoint",
        "finngen:df14",
        "#M13",
        "#GASTRO_CM"
    ],
    "share_token": null,
    "share_expires_at": null,
    "domain": "finngen-endpoint",
    "quality_tier": "draft",
    "deprecated_at": null,
    "superseded_by": null
}