{
    "id": 2909,
    "name": "M13_ENTESOPATHYNAS",
    "description": "Other\/unspecified enthesopathies, not elsewhere classified — FinnGen Endpoint Library (DF14). Source: https:\/\/finngen.fi. Note: cohort generation against a CDM is not yet implemented for this shape; copy to a custom cohort first.",
    "expression_json": {
        "kind": "finngen_endpoint",
        "tags": [
            "#M13",
            "#GASTRO_CM"
        ],
        "level": "4",
        "parent": null,
        "release": "df14",
        "coverage": {
            "pct": 1,
            "bucket": "FULLY_MAPPED",
            "n_tokens_total": 18,
            "n_tokens_resolved": 18
        },
        "conditions": null,
        "provenance": {
            "source_row": 2662,
            "imported_at": "2026-04-17T19:57:04+00:00",
            "source_file": "FINNGEN_ENDPOINTS_DF14_Final_2026-02-13_public.xlsx",
            "importer_version": "1.0.0"
        },
        "hd_mainonly": false,
        "cod_mainonly": false,
        "source_codes": {
            "hd_icd_8": {
                "raw": "7310[5-9]",
                "patterns": [
                    "73105",
                    "73106",
                    "73107",
                    "73108",
                    "73109"
                ]
            },
            "hd_icd_9": {
                "raw": "726[8-9]",
                "patterns": [
                    "7268",
                    "7269"
                ]
            },
            "kela_atc": {
                "raw": null,
                "patterns": []
            },
            "oper_nom": {
                "raw": null,
                "patterns": []
            },
            "canc_topo": {
                "raw": null,
                "patterns": []
            },
            "cod_icd_8": {
                "raw": "7310[5-9]",
                "patterns": [
                    "73105",
                    "73106",
                    "73107",
                    "73108",
                    "73109"
                ]
            },
            "cod_icd_9": {
                "raw": "726[8-9]",
                "patterns": [
                    "7268",
                    "7269"
                ]
            },
            "hd_icd_10": {
                "raw": "M77[8-9]",
                "patterns": [
                    "M778",
                    "M779"
                ]
            },
            "canc_behav": {
                "raw": null,
                "patterns": []
            },
            "canc_morph": {
                "raw": null,
                "patterns": []
            },
            "cod_icd_10": {
                "raw": "M77[8-9]",
                "patterns": [
                    "M778",
                    "M779"
                ]
            },
            "kela_reimb": {
                "raw": null,
                "patterns": []
            },
            "outpat_icd": {
                "raw": null,
                "patterns": []
            },
            "hd_icd_8_excl": {
                "raw": null,
                "patterns": []
            },
            "hd_icd_9_excl": {
                "raw": null,
                "patterns": []
            },
            "hd_icd_10_excl": {
                "raw": null,
                "patterns": []
            },
            "kela_reimb_icd": {
                "raw": null,
                "patterns": []
            }
        },
        "spec_version": "1.0",
        "pre_conditions": null,
        "coverage_bucket": "FULLY_MAPPED",
        "sex_restriction": null,
        "coverage_profile": "partial",
        "include_endpoints": [],
        "resolved_concepts": {
            "truncated": false,
            "drugs_standard": [],
            "source_concept_ids": [
                35209003,
                35209004,
                44819975,
                44828061,
                44837362,
                44837363
            ],
            "conditions_standard": [
                73008,
                75627,
                72715,
                4287786
            ]
        }
    },
    "author_id": 117,
    "is_public": true,
    "version": 1,
    "created_at": "2026-04-16T23:56:11.000000Z",
    "updated_at": "2026-04-17T19:57:04.000000Z",
    "deleted_at": null,
    "tags": [
        "finngen-endpoint",
        "finngen:df14",
        "#M13",
        "#GASTRO_CM"
    ],
    "share_token": null,
    "share_expires_at": null,
    "domain": "finngen-endpoint",
    "quality_tier": "draft",
    "deprecated_at": null,
    "superseded_by": null,
    "coverage_profile": "partial"
}